pynet/__init__.py
pynet/better_connection.py
pynet/better_process.py
pynet/better_thread.py
pynet/client.py
pynet/server.py
pynet/system_header.py
py_network_pynet-0.0.1.dist-info/METADATA
py_network_pynet-0.0.1.dist-info/WHEEL
py_network_pynet-0.0.1.dist-info/licenses/LICENSE
py_network_pynet-0.0.1.dist-info/RECORD
