Metadata-Version: 2.3
Name: py-network-pynet
Version: 0.0.1
Author: Bill Clark
Maintainer: Bill Clark
License-File: LICENSE
Requires-Python: >=3.8
Requires-Dist: crccheck
Requires-Dist: numpy<2.0
Requires-Dist: pytest
Requires-Dist: pytest-cov
Requires-Dist: pyyaml
Requires-Dist: pyzmq>23.0
Requires-Dist: sphinx
Requires-Dist: sphinx-rtd-theme
